slugify_rs-0.1.22.dist-info/METADATA
slugify_rs-0.1.22.dist-info/WHEEL
slugify_rs-0.1.22.dist-info/licenses/LICENSE
slugify_rs/__init__.py
slugify_rs/ffi.py
slugify_rs/libslugify_rs.so
slugify_rs-0.1.22.dist-info/RECORD
