Metadata-Version: 2.4
Name: slugify_rs
Version: 0.1.22
License-File: LICENSE
Home-Page: https://github.com/gmaOCR/slugify-rs
Requires-Python: >=3.8
